generator/__init__.py
generator/cmakelist_generator.py
generator/file_generator.py
generator/mock_generator.py
generator/output_generator.py
generator/test_runner_generator.py
VTunit-0.0.1a0.dist-info/LICENSE.txt
VTunit-0.0.1a0.dist-info/METADATA
VTunit-0.0.1a0.dist-info/WHEEL
VTunit-0.0.1a0.dist-info/top_level.txt
VTunit-0.0.1a0.dist-info/RECORD
