Metadata-Version: 2.1
Name: VTunit
Version: 0.0.1a0
Summary: Unit test helper
Home-page: https://github.com/vtunr/VTunit
Author: Tony Martinet
Author-email: tonymartinet@gmail.com
License: UNKNOWN
Platform: UNKNOWN
Classifier: Programming Language :: Python :: 2.7
Classifier: License :: OSI Approved :: MIT License
Classifier: Operating System :: OS Independent
Requires-Python: >=2.7
Requires-Dist: argparse
Requires-Dist: regex
